microredes/__init__.py
microredes/calc_helper.py
microredes/connection.py
microredes/constants.py
microredes/microredes.py
microredes-0.4.dist-info/LICENSE
microredes-0.4.dist-info/METADATA
microredes-0.4.dist-info/WHEEL
microredes-0.4.dist-info/top_level.txt
microredes-0.4.dist-info/RECORD
