Metadata-Version: 2.1
Name: microredes
Version: 0.4
Summary: Librería para control de una microrred basada en BUS CAN
Home-page: https://github.com/gribera/microredes-lib
Author: Gonzalo Ribera
Author-email: gonzalo.ribera@gmail.com
License: UNKNOWN
Platform: UNKNOWN
Classifier: Programming Language :: Python :: 3
Classifier: License :: OSI Approved :: MIT License
Classifier: Operating System :: OS Independent
Requires-Python: >=3.6
License-File: LICENSE
